gdprCrawler.py
pygdpr/__init__.py
pygdpr/assets/__init__.py
pygdpr/assets/dpa-info.json
pygdpr/assets/dpa-reachability-info.json
pygdpr/assets/dpa-stopwords.json
pygdpr/assets/eu-currencies.json
pygdpr/assets/eu-members.json
pygdpr/assets/gdpr-article-validation-tree.json
pygdpr/assets/gdpr-stopwords.json
pygdpr/models/__init__.py
pygdpr/models/common/__init__.py
pygdpr/models/common/error/__init__.py
pygdpr/models/common/error/google_translate_price_error/__init__.py
pygdpr/models/common/error/max_retries_error/__init__.py
pygdpr/models/common/eu_member/__init__.py
pygdpr/models/common/pagination/__init__.py
pygdpr/models/common/reachability_node/__init__.py
pygdpr/models/document/__init__.py
pygdpr/models/document/metadata/__init__.py
pygdpr/models/document/metadata/summary/__init__.py
pygdpr/models/document/metadata/title/__init__.py
pygdpr/models/document/text/__init__.py
pygdpr/models/dpa/__init__.py
pygdpr/models/dpa/austria/__init__.py
pygdpr/models/dpa/belgium/__init__.py
pygdpr/models/dpa/bulgaria/__init__.py
pygdpr/models/dpa/croatia/__init__.py
pygdpr/models/dpa/cyprus/__init__.py
pygdpr/models/dpa/czech_republic/__init__.py
pygdpr/models/dpa/denmark/__init__.py
pygdpr/models/dpa/edpb/__init__.py
pygdpr/models/dpa/estonia/__init__.py
pygdpr/models/dpa/finland/__init__.py
pygdpr/models/dpa/france/__init__.py
pygdpr/models/dpa/germany/__init__.py
pygdpr/models/dpa/greece/__init__.py
pygdpr/models/dpa/hungary/__init__.py
pygdpr/models/dpa/ireland/__init__.py
pygdpr/models/dpa/italy/__init__.py
pygdpr/models/dpa/latvia/__init__.py
pygdpr/models/dpa/lithuania/__init__.py
pygdpr/models/dpa/luxembourg/__init__.py
pygdpr/models/dpa/malta/__init__.py
pygdpr/models/dpa/netherlands/__init__.py
pygdpr/models/dpa/poland/__init__.py
pygdpr/models/dpa/portugal/__init__.py
pygdpr/models/dpa/romania/__init__.py
pygdpr/models/dpa/slovakia/__init__.py
pygdpr/models/dpa/slovenia/__init__.py
pygdpr/models/dpa/spain/__init__.py
pygdpr/models/dpa/sweden/__init__.py
gdprCrawlerTest20-0.0.1.dist-info/LICENSE
gdprCrawlerTest20-0.0.1.dist-info/METADATA
gdprCrawlerTest20-0.0.1.dist-info/WHEEL
gdprCrawlerTest20-0.0.1.dist-info/entry_points.txt
gdprCrawlerTest20-0.0.1.dist-info/top_level.txt
gdprCrawlerTest20-0.0.1.dist-info/RECORD
